garbage_translator
