Metadata-Version: 2.1
Name: garbage-translator
Version: 0.0.5
Summary: translate to look-alike text in another language
Home-page: https://github.com/Madoshakalaka/garbage-translator
Author: Matt Yan
Author-email: syan4@ualberta.ca
License: UNKNOWN
Project-URL: Bug Reports, https://github.com/Madoshakalaka/garbage-translator/issues
Project-URL: Say Thanks!, https://github.com/Madoshakalaka/garbage-translator
Project-URL: Source, https://github.com/Madoshakalaka/garbage-translator
Platform: UNKNOWN
Classifier: Development Status :: 4 - Beta
Classifier: Intended Audience :: Developers
Classifier: Topic :: Software Development :: Build Tools
Classifier: License :: OSI Approved :: MIT License
Classifier: Programming Language :: Python :: 3.6
Classifier: Programming Language :: Python :: 3.7
Requires-Python: >=3.5
